exeter-0.5.1.dist-info/METADATA
exeter-0.5.1.dist-info/WHEEL
exeter-0.5.1.dist-info/MIT.txt
exeter-0.5.1.data/scripts/exetool
exeter/__init__.py
exeter/asserts.py
exeter/manifest.py
exeter/protocol.py
exeter/scenario.py
exeter/py.typed
exeter-0.5.1.dist-info/RECORD
