Metadata-Version: 2.1
Name: exeter
Version: 0.5.1
Summary: A test protocol for tests independent of language and runner
Author-Email: David Gibson <david@gibson.dropbear.id.au>
License: Permission is hereby granted, free of charge, to any
Classifier: Development Status :: 3 - Alpha
Classifier: Intended Audience :: Developers
Classifier: License :: OSI Approved :: MIT License
Classifier: Programming Language :: Python :: 3
Classifier: Programming Language :: Python :: 3.11
Classifier: Programming Language :: Python :: 3.12
Classifier: Topic :: Software Development :: Testing
Project-URL: Repository, https://gitlab.com/dgibson/exeter
Project-URL: Documentation, https://gitlab.com/dgibson/exeter/-/blob/main/README.md
Requires-Python: >=3.11
